dobro/__init__.py
dobro/cli.py
dobro/dobro.py
dobro-0.4.2.dist-info/LICENSE
dobro-0.4.2.dist-info/METADATA
dobro-0.4.2.dist-info/WHEEL
dobro-0.4.2.dist-info/entry_points.txt
dobro-0.4.2.dist-info/top_level.txt
dobro-0.4.2.dist-info/RECORD
